beencrypted/__init__.py
beencrypted/decrypt.py
beencrypted/encrypt.py
beencrypted-0.0.3.dist-info/LICENSE
beencrypted-0.0.3.dist-info/METADATA
beencrypted-0.0.3.dist-info/WHEEL
beencrypted-0.0.3.dist-info/top_level.txt
beencrypted-0.0.3.dist-info/RECORD
