Metadata-Version: 2.1
Name: beencrypted
Version: 0.0.3
Summary: Encrypt strings to the Bee Movie script and back
Home-page: UNKNOWN
Author: Agent-Kwabbel (Fabe Stuffken)
License: UNKNOWN
Keywords: python,bee,movie,bee movie,encryption,decryption,meme
Platform: UNKNOWN
Classifier: Development Status :: 4 - Beta
Classifier: Intended Audience :: Developers
Classifier: Programming Language :: Python :: 3
Classifier: Operating System :: Unix
Classifier: Operating System :: MacOS :: MacOS X
Classifier: Operating System :: Microsoft :: Windows
License-File: LICENSE
